{
  "outPath": "src/main/resources/templates/doc",
  "serverUrl": "http://localhost:9999",
  "pathPrefix": "management",
  "isStrict": false,
  "allInOne": true,
  "coverOld": true,
  "createDebugPage": true,
  "packageFilters": "com.study.boot.*",
  "style": "xt256",
  "projectName": "quick-login",
  "showAuthor": true,
  "allInOneDocFileName": "doc.html",
  "since": "1.0.0",
  "ignoreRequestParams": [
    "org.springframework.ui.ModelMap"
  ],
  "responseBodyAdvice": {
    "className": "com.study.boot.base.BaseResponse"
  },
  "errorCodeDictionaries": [
    {
      "title": "title",
      "enumClassName": "com.study.boot.base.CommonResponseEnum",
      "codeField": "code",
      "descField": "message"
    }
  ]
}